optima_vis/__init__.py
optima_vis/models/gif_properties.py
optima_vis/models/video_properties.py
optima_vis/services/animation_generator/optimizer_animation_generator.py
optima_vis/services/plot_generator/loss_contour_generator.py
optima_vis/services/plot_generator/optimizer_plot_generator.py
optima_vis-1.4.2.dist-info/METADATA
optima_vis-1.4.2.dist-info/WHEEL
optima_vis-1.4.2.dist-info/top_level.txt
optima_vis-1.4.2.dist-info/RECORD
