Metadata-Version: 2.4
Name: optima_vis
Version: 1.4.2
Summary: A visualization tool for neural network optimizers
Project-URL: Homepage, https://github.com/usernamenenad/optima-vis
Project-URL: Bug Tracker, https://github.com/usernamenenad/optima-vis/issues
Requires-Python: >=3.13
Requires-Dist: matplotlib>=3.10.6
Requires-Dist: numpy>=2.3.2
Requires-Dist: pillow>=11.3.0
Requires-Dist: pytest>=8.4.2
Requires-Dist: torch>=2.8.0
